adi_spo2_watch/__init__.py
adi_spo2_watch/sdk.py
adi_spo2_watch/application/__init__.py
adi_spo2_watch/application/ad7156_application.py
adi_spo2_watch/application/adp5360_application.py
adi_spo2_watch/application/bia_application.py
adi_spo2_watch/application/common_application.py
adi_spo2_watch/application/common_stream.py
adi_spo2_watch/application/csv_logging.py
adi_spo2_watch/application/ecg_application.py
adi_spo2_watch/application/eda_application.py
adi_spo2_watch/application/fs_application.py
adi_spo2_watch/application/low_touch_application.py
adi_spo2_watch/application/lt_mode4_application.py
adi_spo2_watch/application/max30208_application.py
adi_spo2_watch/application/pm_application.py
adi_spo2_watch/application/sensorhub_application.py
adi_spo2_watch/application/session_manager_application.py
adi_spo2_watch/application/test_application.py
adi_spo2_watch/application/user0_application.py
adi_spo2_watch/application/study_watch/__init__.py
adi_spo2_watch/application/vsm_mb_sb/__init__.py
adi_spo2_watch/application/vsm_mb_sb/pm_application.py
adi_spo2_watch/core/__init__.py
adi_spo2_watch/core/ble_manager.py
adi_spo2_watch/core/packet_manager.py
adi_spo2_watch/core/utils.py
adi_spo2_watch/core/data_types/__init__.py
adi_spo2_watch/core/data_types/array.py
adi_spo2_watch/core/data_types/binary.py
adi_spo2_watch/core/data_types/data_type.py
adi_spo2_watch/core/data_types/decimal.py
adi_spo2_watch/core/data_types/enums.py
adi_spo2_watch/core/data_types/integer.py
adi_spo2_watch/core/data_types/string.py
adi_spo2_watch/core/enums/__init__.py
adi_spo2_watch/core/enums/ad7156_enums.py
adi_spo2_watch/core/enums/adp5360_enums.py
adi_spo2_watch/core/enums/bia_enums.py
adi_spo2_watch/core/enums/board_enums.py
adi_spo2_watch/core/enums/common_enums.py
adi_spo2_watch/core/enums/dcb_enums.py
adi_spo2_watch/core/enums/display_enums.py
adi_spo2_watch/core/enums/ecg_enums.py
adi_spo2_watch/core/enums/eda_enums.py
adi_spo2_watch/core/enums/fs_enums.py
adi_spo2_watch-6.10.0.dist-info/licenses/LICENSE
adi_spo2_watch-6.10.0.dist-info/METADATA
adi_spo2_watch-6.10.0.dist-info/WHEEL
adi_spo2_watch-6.10.0.dist-info/top_level.txt
adi_spo2_watch-6.10.0.dist-info/RECORD
