Metadata-Version: 2.4
Name: adi_spo2_watch
Version: 6.10.0
Summary: ADI SpO2 Watch Python SDK
Home-page: https://github.com/analogdevicesinc/spo2-watch-sdk
Author: Analog Devices, Inc.
Author-email: healthcare-support@analog.com
License: BSD 3-Clause License
Classifier: License :: OSI Approved :: BSD License
Classifier: Operating System :: OS Independent
Classifier: Programming Language :: Python :: 3.6
Classifier: Programming Language :: Python :: 3.7
Classifier: Programming Language :: Python :: 3.8
Classifier: Programming Language :: Python :: 3.9
Classifier: Programming Language :: Python :: 3.10
Classifier: Intended Audience :: Healthcare Industry
Classifier: Topic :: Software Development :: Libraries
Requires-Python: >=3.6
License-File: LICENSE
Requires-Dist: pyserial==3.5
Requires-Dist: tqdm==4.61.0
Requires-Dist: libusb1==3.0.0
Dynamic: author
Dynamic: author-email
Dynamic: classifier
Dynamic: description
Dynamic: description-content-type
Dynamic: home-page
Dynamic: license
Dynamic: license-file
Dynamic: requires-dist
Dynamic: requires-python
Dynamic: summary
